django_admin_trap/__init__.py
django_admin_trap/apps.py
django_admin_trap/forms.py
django_admin_trap/urls.py
django_admin_trap/views.py
django_admin_trap/templates/admin_trap/logged_out.html
django_admin_trap/templates/admin_trap/login.html
django_admin_trap-1.1.1.dist-info/licenses/LICENSE
django_admin_trap-1.1.1.dist-info/METADATA
django_admin_trap-1.1.1.dist-info/WHEEL
django_admin_trap-1.1.1.dist-info/top_level.txt
django_admin_trap-1.1.1.dist-info/RECORD
