Metadata-Version: 2.4
Name: django-admin-trap
Version: 1.1.1
Summary: 🚨 Django Admin Trap - The Ultimate Admin Protection System | Fake admin login page for security & honeypots
Home-page: https://github.com/jamil-codes/django-admin-trap
Author: Jamil Ahmed
Author-email: Jamil Ahmed <contact@jamilcodes.com>
Project-URL: Homepage, https://django-admin-trap.jamilcodes.com
Project-URL: Repository, https://github.com/jamil-codes/django-admin-trap
Project-URL: Bug Tracker, https://github.com/jamil-codes/django-admin-trap/issues
Project-URL: Changelog, https://github.com/jamil-codes/django-admin-trap/releases
Keywords: django,security,admin,honeypot,trap,intrusion-detection,cybersecurity,authentication,fake-login,protection
Classifier: Development Status :: 5 - Production/Stable
Classifier: Framework :: Django
Classifier: Framework :: Django :: 4.2
Classifier: Framework :: Django :: 5.0
Classifier: Framework :: Django :: 5.1
Classifier: Intended Audience :: Developers
Classifier: Intended Audience :: System Administrators
Classifier: License :: OSI Approved :: MIT License
Classifier: Operating System :: OS Independent
Classifier: Programming Language :: Python :: 3
Classifier: Programming Language :: Python :: 3.8
Classifier: Programming Language :: Python :: 3.9
Classifier: Programming Language :: Python :: 3.10
Classifier: Programming Language :: Python :: 3.11
Classifier: Programming Language :: Python :: 3.12
Classifier: Programming Language :: Python :: 3.13
Classifier: Topic :: Internet :: WWW/HTTP :: Dynamic Content
Classifier: Topic :: Security
Classifier: Topic :: System :: Monitoring
Classifier: Natural Language :: English
Requires-Python: >=3.8
License-File: LICENSE
Requires-Dist: Django>=4.2
Provides-Extra: dev
Requires-Dist: setuptools>=42; extra == "dev"
Requires-Dist: wheel; extra == "dev"
Requires-Dist: twine; extra == "dev"
Dynamic: author
Dynamic: home-page
Dynamic: license-file
Dynamic: requires-python
